xlsconv/__init__.py
xlsconv/ast.py
xlsconv/django.py
xlsconv/parser.py
xlsconv-2.0.0.dist-info/LICENSE
xlsconv-2.0.0.dist-info/METADATA
xlsconv-2.0.0.dist-info/WHEEL
xlsconv-2.0.0.dist-info/entry_points.txt
xlsconv-2.0.0.dist-info/top_level.txt
xlsconv-2.0.0.dist-info/RECORD
