Metadata-Version: 2.1
Name: xlsconv
Version: 2.0.0
Summary: Tool to convert ODK-style XLSForms into Django models or use with wq (https://wq.io/)
Author-email: "S. Andrew Sheppard" <andrew@wq.io>
License: MIT
Project-URL: Homepage, https://github.com/wq/xlsform-converter
Project-URL: Documentation, https://wq.io/
Project-URL: Source, https://github.com/wq/xlsform-converter
Project-URL: Release Notes, https://github.com/wq/xlsform-converter/releases
Project-URL: Issues, https://github.com/wq/xlsform-converter/issues
Project-URL: Tests, https://github.com/wq/xlsform-converter/actions/workflows/test.yml
Classifier: Development Status :: 5 - Production/Stable
Classifier: Environment :: Web Environment
Classifier: License :: OSI Approved :: MIT License
Classifier: Natural Language :: English
Classifier: Programming Language :: Python :: 3
Classifier: Programming Language :: Python :: 3.7
Classifier: Programming Language :: Python :: 3.8
Classifier: Programming Language :: Python :: 3.9
Classifier: Programming Language :: Python :: 3.10
Classifier: Programming Language :: Python :: 3.11
Classifier: Topic :: Software Development :: Code Generators
Classifier: Framework :: Django
Classifier: Topic :: Text Processing :: Markup :: HTML
Requires-Python: >=3.7
License-File: LICENSE
Requires-Dist: pyxform
Requires-Dist: astunparse
Requires-Dist: black
